atr_dan-0.2.2rc2.dist-info/licenses/LICENCE
atr_dan-0.2.2rc2.dist-info/licenses/LICENSE
dan/__init__.py
dan/bio.py
dan/cli.py
dan/utils.py
dan/datasets/__init__.py
dan/datasets/utils.py
dan/datasets/analyze/__init__.py
dan/datasets/analyze/statistics.py
dan/datasets/download/__init__.py
dan/datasets/download/exceptions.py
dan/datasets/download/images.py
dan/datasets/download/utils.py
dan/datasets/entities/__init__.py
dan/datasets/entities/extract.py
dan/datasets/extract/__init__.py
dan/datasets/extract/arkindex.py
dan/datasets/extract/db.py
dan/datasets/extract/exceptions.py
dan/datasets/extract/utils.py
dan/datasets/language_model/__init__.py
dan/datasets/language_model/build.py
dan/datasets/language_model/utils.py
dan/datasets/tokens/__init__.py
dan/datasets/tokens/generate.py
dan/ocr/__init__.py
dan/ocr/decoder.py
dan/ocr/encoder.py
dan/ocr/evaluate.py
dan/ocr/mlflow.py
dan/ocr/schedulers.py
dan/ocr/train.py
dan/ocr/transforms.py
dan/ocr/utils.py
dan/ocr/wandb.py
dan/ocr/manager/__init__.py
dan/ocr/manager/dataset.py
dan/ocr/manager/metrics.py
dan/ocr/manager/ocr.py
dan/ocr/manager/training.py
dan/ocr/predict/__init__.py
dan/ocr/predict/attention.py
dan/ocr/predict/inference.py
tests/__init__.py
tests/conftest.py
tests/test_analyze.py
tests/test_attention.py
tests/test_bio.py
tests/test_db.py
tests/test_download.py
tests/test_entities.py
tests/test_evaluate.py
tests/test_extract.py
tests/test_language_model.py
tests/test_prediction.py
tests/test_tokens.py
tests/test_training.py
tests/test_utils.py
atr_dan-0.2.2rc2.dist-info/METADATA
atr_dan-0.2.2rc2.dist-info/WHEEL
atr_dan-0.2.2rc2.dist-info/entry_points.txt
atr_dan-0.2.2rc2.dist-info/top_level.txt
atr_dan-0.2.2rc2.dist-info/RECORD
