Metadata-Version: 2.4
Name: atr-dan
Version: 0.2.2rc2
Summary: Teklia DAN
Author-email: Teklia <contact@teklia.com>
Project-URL: Homepage, https://atr.pages.teklia/dan/
Project-URL: Documentation, https://atr.pages.teklia/dan/
Project-URL: Repository, https://gitlab.teklia.com/atr/dan
Project-URL: Bug Tracker, https://gitlab.teklia.com/atr/dan/issues
Project-URL: Maintainers, https://teklia.com
Keywords: python,HTR,OCR,NER,machine learning,pytorch
Classifier: Development Status :: 4 - Beta
Classifier: License :: CeCILL-C Free Software License Agreement (CECILL-C)
Classifier: Programming Language :: Python :: 3 :: Only
Classifier: Programming Language :: Python :: 3.10
Classifier: Programming Language :: Python :: 3.11
Classifier: Programming Language :: Python :: 3.12
Classifier: Topic :: Software Development :: Libraries :: Python Modules
Classifier: Topic :: Text Processing :: Linguistic
Classifier: Topic :: Scientific/Engineering :: Artificial Intelligence
Classifier: Topic :: Scientific/Engineering :: Image Recognition
Requires-Python: >=3.10
License-File: LICENSE
License-File: LICENCE
Requires-Dist: albumentations==1.4.19
Requires-Dist: arkindex-export==0.1.12
Requires-Dist: flashlight-text==0.0.7
Requires-Dist: imageio==2.26.1
Requires-Dist: imagesize==1.4.1
Requires-Dist: lxml==5.2.1
Requires-Dist: matplotlib==3.8.3
Requires-Dist: mdutils==1.6.0
Requires-Dist: nltk==3.9.1
Requires-Dist: numpy==1.26.0
Requires-Dist: PyYAML==6.0.2
Requires-Dist: scipy==1.12.0
Requires-Dist: sentencepiece==0.2.0
Requires-Dist: teklia-line-image-extractor==0.6.0
Requires-Dist: teklia-nerval==0.3.3
Requires-Dist: tenacity==8.2.3
Requires-Dist: tensorboard==2.17.0
Requires-Dist: torch==2.4.0
Requires-Dist: torchaudio==2.4.0
Requires-Dist: torchvision==0.19.0
Requires-Dist: tqdm==4.66.5
Requires-Dist: wandb==0.17.0
Provides-Extra: mlflow
Requires-Dist: mlflow-skinny==2.2.2; extra == "mlflow"
Requires-Dist: pandas==2.2.3; extra == "mlflow"
Requires-Dist: boto3==1.26.124; extra == "mlflow"
Dynamic: license-file
